discordbot_bc_editor/__init__.py
discordbot_bc_editor/__main__.py
discordbot_bc_editor/adb_handler.py
discordbot_bc_editor/config_manager.py
discordbot_bc_editor/csv_handler.py
discordbot_bc_editor/feature_handler.py
discordbot_bc_editor/game_data_getter.py
discordbot_bc_editor/helper.py
discordbot_bc_editor/item.py
discordbot_bc_editor/locale_handler.py
discordbot_bc_editor/managed_item.py
discordbot_bc_editor/parse_save.py
discordbot_bc_editor/patcher.py
discordbot_bc_editor/root_handler.py
discordbot_bc_editor/serialise_save.py
discordbot_bc_editor/server_handler.py
discordbot_bc_editor/tracker.py
discordbot_bc_editor/updater.py
discordbot_bc_editor/user_input_handler.py
discordbot_bc_editor/edits/__init__.py
discordbot_bc_editor/edits/basic/__init__.py
discordbot_bc_editor/edits/basic/basic_items.py
discordbot_bc_editor/edits/basic/catfruit.py
discordbot_bc_editor/edits/basic/catseyes.py
discordbot_bc_editor/edits/basic/ototo_base_mats.py
discordbot_bc_editor/edits/basic/talent_orbs.py
discordbot_bc_editor/edits/basic/talent_orbs_new.py
discordbot_bc_editor/edits/cats/__init__.py
discordbot_bc_editor/edits/cats/cat_helper.py
discordbot_bc_editor/edits/cats/cat_id_selector.py
discordbot_bc_editor/edits/cats/chara_drop.py
discordbot_bc_editor/edits/cats/clear_cat_guide.py
discordbot_bc_editor/edits/cats/evolve_cats.py
discordbot_bc_editor/edits/cats/get_remove_cats.py
discordbot_bc_editor/edits/cats/talents.py
discordbot_bc_editor/edits/cats/upgrade_blue.py
discordbot_bc_editor/edits/cats/upgrade_cats.py
discordbot_bc_editor/edits/gamototo/__init__.py
discordbot_bc_editor/edits/gamototo/fix_gamatoto.py
discordbot_bc_editor/edits/gamototo/gamatoto_xp.py
discordbot_bc_editor/edits/gamototo/helpers.py
discordbot_bc_editor/edits/gamototo/ototo_cat_cannon.py
discordbot_bc_editor/edits/levels/__init__.py
discordbot_bc_editor/edits/levels/aku.py
discordbot_bc_editor/edits/levels/allow_filibuster_clearing.py
discordbot_bc_editor/edits/levels/behemoth_culling.py
discordbot_bc_editor-0.0.1.dist-info/METADATA
discordbot_bc_editor-0.0.1.dist-info/WHEEL
discordbot_bc_editor-0.0.1.dist-info/top_level.txt
discordbot_bc_editor-0.0.1.dist-info/RECORD
